<?xml version = '1.0' encoding = 'UTF-8'?>
<Diagram class="oracle.dbtools.crest.swingui.datatypes.DPVDataTypes" id="3D1E7BEC-16DD-B8A2-3FAC-FF3DE197A6A7">
<createdBy>Patty Reyes</createdBy>
<modifiedBy>Patty Reyes</modifiedBy>
<createdTime>2024-03-06 19:53:20 UTC</createdTime>
<autoRoute>false</autoRoute>
<boxInbox>true</boxInbox>
<showLegend>false</showLegend>
<showLabels>true</showLabels>
<showRelAttributes>false</showRelAttributes>
<gridEnabled>false</gridEnabled>
<showGrid>false</showGrid>
<diagramColor>-1</diagramColor>
<display>false</display>
<notation>1</notation>
<objectViews>
<OView class="oracle.dbtools.crest.swingui.datatypes.TVStructuredType" oid="47E390DE-0671-C4B1-8428-0F45CBEE18F8" otype="StructuredType" vid="6DBF03CE-D5E7-5686-C7B6-4468A0F7B0BF">
<hideElementsInCurrentOnly>false</hideElementsInCurrentOnly>
<bounds x="20" y="20" width="100" height="100"/>
</OView>
<OView class="oracle.dbtools.crest.swingui.datatypes.TVStructuredType" oid="F72C39E0-D1CA-8821-2AD7-A1E95A37D3D1" otype="StructuredType" vid="8261CB37-6C4B-3DD4-1F6A-80CCEB9356A8">
<hideElementsInCurrentOnly>false</hideElementsInCurrentOnly>
<bounds x="20" y="20" width="100" height="100"/>
</OView>
</objectViews>
</Diagram>